{
  "version": 1,
  "goal": "Remove AI slop from every source file",
  "maxAttempts": 3,
  "tasks": [
    {
      "id": 1,
      "description": "Clean src/engine.ts — remove all narrating comments like '// Build column list for better-sqlite3', '// Key columns become hidden parameters', '// Filter out key columns...', '// Always add connection as a parameter', '// Map parameter values to key column quals', '// Connection parameter is last', '// Resolve connection', '// Check cache', '// Rate limit', '// Decide get vs list', '// Use get only when ALL key columns have quals', '// Hydrate if needed', '// Cache results', '// Release rate limiter', '// Yield rows, picking only declared columns', '// Configure rate limits', '// Register all tables from all plugins'. Keep the code exactly the same, just strip these comments.",
      "check": {
        "command": "npx tsx -e \"import { QueryEngine } from './src/engine.js'; console.log('ok')\" && ! grep -n '// Build column\\|// Key columns become\\|// Filter out key\\|// Always add connection\\|// Map parameter\\|// Connection parameter\\|// Resolve connection\\|// Check cache\\|// Rate limit\\|// Decide get\\|// Use get only\\|// Hydrate if\\|// Cache results\\|// Release rate\\|// Yield rows\\|// Configure rate\\|// Register all' src/engine.ts"
      },
      "status": "done",
      "attempts": 1,
      "maxAttempts": 3,
      "startedAt": "2026-03-20T07:59:13.049Z",
      "finishedAt": "2026-03-20T07:59:30.891Z",
      "summary": "done"
    },
    {
      "id": 2,
      "description": "Clean src/index.ts — remove all section header comments: '// ── SDK entrypoint ──', '// Import dripline as a library:', '//   import { Dripline } from \"dripline\";', '// Core engine', '// Plugin SDK — everything needed to write a plugin', '// Plugin API (for writing plugins)', '// Plugin installer', '// Config', '// Cache & Rate Limiter', '// Formatters', '// HTTP utilities for plugin authors', '// Built-in plugins'. Just keep the exports, no comments.",
      "check": {
        "command": "npx tsx -e \"import { Dripline } from './src/index.js'; console.log('ok')\" && ! grep '// ' src/index.ts"
      },
      "status": "done",
      "attempts": 1,
      "maxAttempts": 3,
      "startedAt": "2026-03-20T07:59:30.926Z",
      "finishedAt": "2026-03-20T07:59:39.633Z",
      "summary": "done"
    },
    {
      "id": 3,
      "description": "Clean src/commands/repl.ts — remove comments: '// Show key columns that aren't in columns list (parameters)', '// Access cache through engine — we'll need to expose it', '// Load history', '// Meta-commands', '// Save to history'.",
      "check": {
        "command": "! grep -n '// Show key\\|// Access cache\\|// Load history\\|// Meta-commands\\|// Save to history' src/commands/repl.ts"
      },
      "status": "done",
      "attempts": 1,
      "maxAttempts": 3,
      "startedAt": "2026-03-20T07:59:39.664Z",
      "finishedAt": "2026-03-20T07:59:47.154Z",
      "summary": "done"
    },
    {
      "id": 4,
      "description": "Clean src/plugin/installer.ts — remove comments: '// npm:@scope/pkg@version or npm:pkg', '// Handle @scope/pkg@version', '// Scoped: @scope/pkg@version', '// git:github.com/user/repo@ref or https://...', '// Normalize to https URL', '// Local path', '// Register in plugins.json', '// Remove files for npm/git installs'.",
      "check": {
        "command": "npx tsx -e \"import { parsePluginSource } from './src/plugin/installer.js'; console.log('ok')\" && ! grep '// npm:\\|// Handle @scope\\|// Scoped:\\|// git:github\\|// Normalize to\\|// Local path\\|// Register in\\|// Remove files' src/plugin/installer.ts"
      },
      "status": "done",
      "attempts": 1,
      "maxAttempts": 3,
      "startedAt": "2026-03-20T07:59:47.184Z",
      "finishedAt": "2026-03-20T07:59:58.292Z",
      "summary": "done"
    },
    {
      "id": 5,
      "description": "Clean src/plugin/loader.ts — remove comments: '// skip invalid plugins', '// skip invalid', '// Check for index.ts/index.js', '// Check for package.json with dripline.plugins', '// skip', '// skip malformed', '// 1. Built-in plugins', '// 2. Project-local: .dripline/plugins/', '// Also load from plugins.json', '// 3. Global: ~/.dripline/plugins/'.",
      "check": {
        "command": "! grep -n '// skip\\|// Check for\\|// 1\\. Built\\|// 2\\. Project\\|// Also load\\|// 3\\. Global' src/plugin/loader.ts"
      },
      "status": "done",
      "attempts": 1,
      "maxAttempts": 3,
      "startedAt": "2026-03-20T07:59:58.325Z",
      "finishedAt": "2026-03-20T08:00:10.010Z",
      "summary": "done"
    },
    {
      "id": 6,
      "description": "Clean src/plugin/api.ts — remove JSDoc comments '/** Check if a value is a PluginFunction (vs a static PluginDef) */' and '/** Resolve a plugin export (function or static) to a PluginDef */'.",
      "check": {
        "command": "! grep '/\\*\\*' src/plugin/api.ts"
      },
      "status": "done",
      "attempts": 1,
      "maxAttempts": 3,
      "startedAt": "2026-03-20T08:00:10.041Z",
      "finishedAt": "2026-03-20T08:00:18.852Z",
      "summary": "done"
    },
    {
      "id": 7,
      "description": "Clean src/plugins/utils/http.ts — remove comments: '// Response has: headers\\r\\n\\r\\nbody\\nstatus_code', '// Parse response headers', '// Last line is status code', '// Parse Link header for next page'.",
      "check": {
        "command": "! grep '// Response has\\|// Parse response\\|// Last line\\|// Parse Link' src/plugins/utils/http.ts"
      },
      "status": "done",
      "attempts": 1,
      "maxAttempts": 3,
      "startedAt": "2026-03-20T08:00:18.887Z",
      "finishedAt": "2026-03-20T08:00:29.732Z",
      "summary": "done"
    },
    {
      "id": 8,
      "description": "Clean src/rate-limiter.ts — remove comments: '// Busy-wait for sync context (virtual table generators are sync)', '// spin', '// busy wait'.",
      "check": {
        "command": "! grep '// Busy-wait\\|// spin\\|// busy wait' src/rate-limiter.ts"
      },
      "status": "done",
      "attempts": 1,
      "maxAttempts": 3,
      "startedAt": "2026-03-20T08:00:29.763Z",
      "finishedAt": "2026-03-20T08:00:37.700Z",
      "summary": "done"
    },
    {
      "id": 9,
      "description": "Clean src/sdk.ts — remove the large JSDoc block (/** ... Dripline SDK — query cloud APIs using SQL ... @example ... */), remove inline comments: '// Re-create engine to pick up the new plugin's tables', '// cache is enabled if it exists'. Keep the short /** method docs */ on public methods.",
      "check": {
        "command": "! grep 'Re-create engine\\|cache is enabled if\\|query cloud APIs using SQL' src/sdk.ts"
      },
      "status": "done",
      "attempts": 1,
      "maxAttempts": 3,
      "startedAt": "2026-03-20T08:00:37.731Z",
      "finishedAt": "2026-03-20T08:00:57.041Z",
      "summary": "done"
    },
    {
      "id": 10,
      "description": "Clean src/utils/table-formatter.ts — remove comments: '// Calculate column widths', '// Cap widths to fit terminal', '// │ between each + edges', '// 1 space each side', '// Top border', '// Header', '// Header separator', '// Data rows', '// Bottom border'.",
      "check": {
        "command": "! grep '// Calculate column\\|// Cap widths\\|// │ between\\|// 1 space\\|// Top border\\|// Header$\\|// Header sep\\|// Data rows\\|// Bottom border' src/utils/table-formatter.ts"
      },
      "status": "done",
      "attempts": 1,
      "maxAttempts": 3,
      "startedAt": "2026-03-20T08:00:57.072Z",
      "finishedAt": "2026-03-20T08:01:06.403Z",
      "summary": "done"
    },
    {
      "id": 11,
      "description": "Clean src/utils/exit-codes.ts — remove inline comments '// Invalid input, missing args' and '// Data directory not found'.",
      "check": {
        "command": "! grep '// Invalid\\|// Data directory' src/utils/exit-codes.ts"
      },
      "status": "done",
      "attempts": 1,
      "maxAttempts": 3,
      "startedAt": "2026-03-20T08:01:06.433Z",
      "finishedAt": "2026-03-20T08:01:13.840Z",
      "summary": "done"
    },
    {
      "id": 12,
      "description": "Clean src/main.ts — remove comment '// Default to REPL when no command given'.",
      "check": {
        "command": "! grep '// Default to' src/main.ts"
      },
      "status": "done",
      "attempts": 1,
      "maxAttempts": 3,
      "startedAt": "2026-03-20T08:01:13.872Z",
      "finishedAt": "2026-03-20T08:01:21.242Z",
      "summary": "done"
    },
    {
      "id": 13,
      "description": "Clean README.md — remove 'A lightweight Steampipe alternative built on SQLite virtual tables. No PostgreSQL, no FDW, no heavyweight dependencies', remove 'Plugins use a function-based API inspired by pi\\'s extensions:', remove the entire '## vs Steampipe' comparison table section. Keep the rest.",
      "check": {
        "command": "! grep -i 'steampipe\\|inspired by pi' README.md"
      },
      "status": "done",
      "attempts": 1,
      "maxAttempts": 3,
      "startedAt": "2026-03-20T08:01:21.276Z",
      "finishedAt": "2026-03-20T08:01:50.571Z",
      "summary": "done"
    },
    {
      "id": 14,
      "description": "Final pass — run all tests to make sure nothing broke.",
      "check": {
        "command": "npm test 2>&1 | tail -5"
      },
      "status": "done",
      "attempts": 1,
      "maxAttempts": 3,
      "startedAt": "2026-03-20T08:01:50.601Z",
      "finishedAt": "2026-03-20T08:02:24.469Z",
      "summary": "212 tests pass"
    }
  ],
  "log": [
    {
      "timestamp": "2026-03-20T07:59:13.049Z",
      "taskId": 1,
      "event": "start",
      "message": "Attempt 1/3: Clean src/engine.ts — remove all narrating comments like '// Build column list for better-sqlite3', '// Key columns become hidden parameters', '// Filter out key columns...', '// Always add connection as a parameter', '// Map parameter values to key column quals', '// Connection parameter is last', '// Resolve connection', '// Check cache', '// Rate limit', '// Decide get vs list', '// Use get only when ALL key columns have quals', '// Hydrate if needed', '// Cache results', '// Release rate limiter', '// Yield rows, picking only declared columns', '// Configure rate limits', '// Register all tables from all plugins'. Keep the code exactly the same, just strip these comments."
    },
    {
      "timestamp": "2026-03-20T07:59:30.891Z",
      "taskId": 1,
      "event": "done",
      "message": "done"
    },
    {
      "timestamp": "2026-03-20T07:59:30.926Z",
      "taskId": 2,
      "event": "start",
      "message": "Attempt 1/3: Clean src/index.ts — remove all section header comments: '// ── SDK entrypoint ──', '// Import dripline as a library:', '//   import { Dripline } from \"dripline\";', '// Core engine', '// Plugin SDK — everything needed to write a plugin', '// Plugin API (for writing plugins)', '// Plugin installer', '// Config', '// Cache & Rate Limiter', '// Formatters', '// HTTP utilities for plugin authors', '// Built-in plugins'. Just keep the exports, no comments."
    },
    {
      "timestamp": "2026-03-20T07:59:39.633Z",
      "taskId": 2,
      "event": "done",
      "message": "done"
    },
    {
      "timestamp": "2026-03-20T07:59:39.664Z",
      "taskId": 3,
      "event": "start",
      "message": "Attempt 1/3: Clean src/commands/repl.ts — remove comments: '// Show key columns that aren't in columns list (parameters)', '// Access cache through engine — we'll need to expose it', '// Load history', '// Meta-commands', '// Save to history'."
    },
    {
      "timestamp": "2026-03-20T07:59:47.154Z",
      "taskId": 3,
      "event": "done",
      "message": "done"
    },
    {
      "timestamp": "2026-03-20T07:59:47.184Z",
      "taskId": 4,
      "event": "start",
      "message": "Attempt 1/3: Clean src/plugin/installer.ts — remove comments: '// npm:@scope/pkg@version or npm:pkg', '// Handle @scope/pkg@version', '// Scoped: @scope/pkg@version', '// git:github.com/user/repo@ref or https://...', '// Normalize to https URL', '// Local path', '// Register in plugins.json', '// Remove files for npm/git installs'."
    },
    {
      "timestamp": "2026-03-20T07:59:58.292Z",
      "taskId": 4,
      "event": "done",
      "message": "done"
    },
    {
      "timestamp": "2026-03-20T07:59:58.325Z",
      "taskId": 5,
      "event": "start",
      "message": "Attempt 1/3: Clean src/plugin/loader.ts — remove comments: '// skip invalid plugins', '// skip invalid', '// Check for index.ts/index.js', '// Check for package.json with dripline.plugins', '// skip', '// skip malformed', '// 1. Built-in plugins', '// 2. Project-local: .dripline/plugins/', '// Also load from plugins.json', '// 3. Global: ~/.dripline/plugins/'."
    },
    {
      "timestamp": "2026-03-20T08:00:10.010Z",
      "taskId": 5,
      "event": "done",
      "message": "done"
    },
    {
      "timestamp": "2026-03-20T08:00:10.041Z",
      "taskId": 6,
      "event": "start",
      "message": "Attempt 1/3: Clean src/plugin/api.ts — remove JSDoc comments '/** Check if a value is a PluginFunction (vs a static PluginDef) */' and '/** Resolve a plugin export (function or static) to a PluginDef */'."
    },
    {
      "timestamp": "2026-03-20T08:00:18.852Z",
      "taskId": 6,
      "event": "done",
      "message": "done"
    },
    {
      "timestamp": "2026-03-20T08:00:18.887Z",
      "taskId": 7,
      "event": "start",
      "message": "Attempt 1/3: Clean src/plugins/utils/http.ts — remove comments: '// Response has: headers\\r\\n\\r\\nbody\\nstatus_code', '// Parse response headers', '// Last line is status code', '// Parse Link header for next page'."
    },
    {
      "timestamp": "2026-03-20T08:00:29.732Z",
      "taskId": 7,
      "event": "done",
      "message": "done"
    },
    {
      "timestamp": "2026-03-20T08:00:29.763Z",
      "taskId": 8,
      "event": "start",
      "message": "Attempt 1/3: Clean src/rate-limiter.ts — remove comments: '// Busy-wait for sync context (virtual table generators are sync)', '// spin', '// busy wait'."
    },
    {
      "timestamp": "2026-03-20T08:00:37.700Z",
      "taskId": 8,
      "event": "done",
      "message": "done"
    },
    {
      "timestamp": "2026-03-20T08:00:37.731Z",
      "taskId": 9,
      "event": "start",
      "message": "Attempt 1/3: Clean src/sdk.ts — remove the large JSDoc block (/** ... Dripline SDK — query cloud APIs using SQL ... @example ... */), remove inline comments: '// Re-create engine to pick up the new plugin's tables', '// cache is enabled if it exists'. Keep the short /** method docs */ on public methods."
    },
    {
      "timestamp": "2026-03-20T08:00:57.041Z",
      "taskId": 9,
      "event": "done",
      "message": "done"
    },
    {
      "timestamp": "2026-03-20T08:00:57.072Z",
      "taskId": 10,
      "event": "start",
      "message": "Attempt 1/3: Clean src/utils/table-formatter.ts — remove comments: '// Calculate column widths', '// Cap widths to fit terminal', '// │ between each + edges', '// 1 space each side', '// Top border', '// Header', '// Header separator', '// Data rows', '// Bottom border'."
    },
    {
      "timestamp": "2026-03-20T08:01:06.403Z",
      "taskId": 10,
      "event": "done",
      "message": "done"
    },
    {
      "timestamp": "2026-03-20T08:01:06.433Z",
      "taskId": 11,
      "event": "start",
      "message": "Attempt 1/3: Clean src/utils/exit-codes.ts — remove inline comments '// Invalid input, missing args' and '// Data directory not found'."
    },
    {
      "timestamp": "2026-03-20T08:01:13.840Z",
      "taskId": 11,
      "event": "done",
      "message": "done"
    },
    {
      "timestamp": "2026-03-20T08:01:13.872Z",
      "taskId": 12,
      "event": "start",
      "message": "Attempt 1/3: Clean src/main.ts — remove comment '// Default to REPL when no command given'."
    },
    {
      "timestamp": "2026-03-20T08:01:21.243Z",
      "taskId": 12,
      "event": "done",
      "message": "done"
    },
    {
      "timestamp": "2026-03-20T08:01:21.276Z",
      "taskId": 13,
      "event": "start",
      "message": "Attempt 1/3: Clean README.md — remove 'A lightweight Steampipe alternative built on SQLite virtual tables. No PostgreSQL, no FDW, no heavyweight dependencies', remove 'Plugins use a function-based API inspired by pi\\'s extensions:', remove the entire '## vs Steampipe' comparison table section. Keep the rest."
    },
    {
      "timestamp": "2026-03-20T08:01:50.571Z",
      "taskId": 13,
      "event": "done",
      "message": "done"
    },
    {
      "timestamp": "2026-03-20T08:01:50.601Z",
      "taskId": 14,
      "event": "start",
      "message": "Attempt 1/3: Final pass — run all tests to make sure nothing broke."
    },
    {
      "timestamp": "2026-03-20T08:02:24.469Z",
      "taskId": 14,
      "event": "done",
      "message": "212 tests pass"
    }
  ],
  "createdAt": "2026-03-20T07:58:23.437Z",
  "updatedAt": "2026-03-20T08:02:24.469Z"
}
